{
  "name": "Fysioklinikk",
  "address": "Helsegata 2, 5432 Bergen",
  "phone_number": "+47 987 65 432",
  "services": [
    {"name": "Fysioterapi konsultasjon", "price": 700, "duration_minutes": 60},
    {"name": "Massasje", "price": 600, "duration_minutes": 45},
    {"name": "Trykkbølgeterapi", "price": 800, "duration_minutes": 45},
    {"name": "Rehabiliteringsprogram", "price": 1200, "duration_minutes": 90}
  ],
  "faq": [
    {
      "question": "Trenger jeg henvisning fra lege?",
      "answer": "Du trenger ikke henvisning for å bestille time hos oss, men vi anbefaler at du konsulterer fastlegen hvis du er usikker."
    },
    {
      "question": "Har dere parkering?",
      "answer": "Ja, vi har gratis kundeparkering ved klinikken."
    }
  ]
}
